<?xml version="1.0" encoding="utf-8"?>
<items>
<item><name>诡秘之主</name><author>爱潜水的乌贼</author></item>
<item><name>圣光</name><author>通吃道人.QD</author></item>
<item><name>我师兄实在太稳健了</name><author>言归正传</author></item>
<item><name>平平无奇大师兄</name><author>黑夜弥天</author></item>
<item><name>亏成首富从游戏开始</name><author>青衫取醉</author></item>
<item><name>这号有毒</name><author>幼儿园一把手</author></item>
<item><name>万族之劫</name><author>老鹰吃小鸡</author></item>
<item><name>东晋北府一丘八</name><author>指云笑天道1</author></item>
<item><name>明天下</name><author>孑与2</author></item>
<item><name>第一序列</name><author>会说话的肘子</author></item>
<item><name>九星毒奶</name><author>育</author></item>
<item><name>暗月纪元</name><author>仐三</author></item>
<item><name>我的外挂跑路了</name><author>幻羽</author></item>
<item><name>当医生开了外挂</name><author>手握寸关尺</author></item>
<item><name>明日之劫</name><author>熊狼狗</author></item>
<item><name>精灵掌门人</name><author>轻泉流响</author></item>
<item><name>轮回乐园</name><author>那一只蚊子</author></item>
<item><name>峡谷之巅</name><author>神秘的大西瓜</author></item>
<item><name>我真不是仙二代</name><author>明月地上霜</author></item>
<item><name>烂柯棋缘</name><author>真费事</author></item>
</items>